erc1820_predeployed/__init__.py
erc1820_predeployed/address.py
erc1820_predeployed/erc1820_registry_generator.py
erc1820_predeployed/py.typed
erc1820_predeployed/artifacts/.keep
erc1820_predeployed/artifacts/ERC1820Registry.json
erc1820_predeployed/artifacts/ERC1820Registry.meta.json
erc1820_predeployed-0.0.1a1.dist-info/METADATA
erc1820_predeployed-0.0.1a1.dist-info/WHEEL
erc1820_predeployed-0.0.1a1.dist-info/top_level.txt
erc1820_predeployed-0.0.1a1.dist-info/RECORD
